{"version":3,"kind":"Article","sha256":"b5446cebd5667957c24cda3896043a843bcf4398d68c80ed32b4401c089ee8fa","slug":"intro","location":"/lecture/general_information/intro.md","dependencies":[],"frontmatter":{"title":"Intro","content_includes_title":false,"authors":[{"id":"contributors-myst-generated-uid-0"}],"license":{"content":{"name":"SD 3-Clause License"}},"github":"https://github.com/luciebinder/testjb2","copyright":"2022","source_url":"https://github.com/luciebinder/testjb2/blob/main/lecture/general_information/intro.md","edit_url":"https://github.com/luciebinder/testjb2/edit/main/lecture/general_information/intro.md","exports":[{"format":"md","filename":"intro.md","url":"/testjb2/build/intro-8cdbc015b297de0ba563b5e04e15c044.md"}]},"mdast":{"type":"root","children":[{"type":"block","children":[{"type":"paragraph","position":{"start":{"line":4,"column":1},"end":{"line":4,"column":1}},"children":[{"type":"text","value":"In the first block of this course we will focus on X","position":{"start":{"line":4,"column":1},"end":{"line":4,"column":1}},"key":"QG6k1qEswR"}],"key":"O92Ignz8S2"},{"type":"heading","depth":2,"position":{"start":{"line":6,"column":1},"end":{"line":6,"column":1}},"children":[{"type":"text","value":"Objectives 📍","position":{"start":{"line":6,"column":1},"end":{"line":6,"column":1}},"key":"qy4fIDFvt8"}],"identifier":"objectives","label":"Objectives 📍","html_id":"objectives","implicit":true,"key":"vyJPYEdqYS"},{"type":"list","ordered":false,"spread":false,"position":{"start":{"line":7,"column":1},"end":{"line":14,"column":1}},"children":[{"type":"listItem","spread":true,"position":{"start":{"line":7,"column":1},"end":{"line":10,"column":1}},"children":[{"type":"paragraph","position":{"start":{"line":7,"column":1},"end":{"line":7,"column":1}},"children":[{"type":"text","value":"Learn about X","position":{"start":{"line":7,"column":1},"end":{"line":7,"column":1}},"key":"BhPiw445qt"}],"key":"vBX3APkdPv"},{"type":"list","ordered":false,"spread":false,"position":{"start":{"line":8,"column":1},"end":{"line":10,"column":1}},"children":[{"type":"listItem","spread":true,"position":{"start":{"line":8,"column":1},"end":{"line":8,"column":1}},"children":[{"type":"paragraph","children":[{"type":"text","value":"What?","position":{"start":{"line":8,"column":1},"end":{"line":8,"column":1}},"key":"Yxi91krYfe"}],"key":"E6yjTcP1Cx"}],"key":"AoqU0zOua0"},{"type":"listItem","spread":true,"position":{"start":{"line":9,"column":1},"end":{"line":10,"column":1}},"children":[{"type":"paragraph","children":[{"type":"text","value":"How?","position":{"start":{"line":9,"column":1},"end":{"line":9,"column":1}},"key":"mcB46EGHGE"}],"key":"KjnaZp4fnD"}],"key":"GsPhsgTNOf"}],"key":"vHD52g6GSF"}],"key":"f9tdF8ZZuD"},{"type":"listItem","spread":true,"position":{"start":{"line":11,"column":1},"end":{"line":11,"column":1}},"children":[{"type":"paragraph","position":{"start":{"line":11,"column":1},"end":{"line":11,"column":1}},"children":[{"type":"text","value":"get the necessary software","position":{"start":{"line":11,"column":1},"end":{"line":11,"column":1}},"key":"Jcz2UmcUfB"}],"key":"zHx9IatJ3q"}],"key":"D78tNL5Gaq"},{"type":"listItem","spread":true,"position":{"start":{"line":12,"column":1},"end":{"line":14,"column":1}},"children":[{"type":"paragraph","position":{"start":{"line":12,"column":1},"end":{"line":12,"column":1}},"children":[{"type":"text","value":"Ask and answer questions","position":{"start":{"line":12,"column":1},"end":{"line":12,"column":1}},"key":"qWvcwttpKZ"}],"key":"ePQzKxFTXc"}],"key":"uwbicg0v4f"}],"key":"XISoGFts5I"},{"type":"heading","depth":2,"position":{"start":{"line":15,"column":1},"end":{"line":15,"column":1}},"children":[{"type":"text","value":"Prerequisities","position":{"start":{"line":15,"column":1},"end":{"line":15,"column":1}},"key":"Fyzl5UrgMR"}],"identifier":"prerequisities","label":"Prerequisities","html_id":"prerequisities","implicit":true,"key":"epvuOTHCxn"},{"type":"list","ordered":false,"spread":false,"position":{"start":{"line":17,"column":1},"end":{"line":19,"column":1}},"children":[{"type":"listItem","spread":true,"position":{"start":{"line":17,"column":1},"end":{"line":17,"column":1}},"children":[{"type":"paragraph","children":[{"type":"text","value":"list prerequisities","position":{"start":{"line":17,"column":1},"end":{"line":17,"column":1}},"key":"UGIqBpq5u2"}],"key":"nzMLga22k1"}],"key":"dAax2OMVRJ"},{"type":"listItem","spread":true,"position":{"start":{"line":18,"column":1},"end":{"line":19,"column":1}},"children":[{"type":"paragraph","children":[{"type":"text","value":"refer back to setup page","position":{"start":{"line":18,"column":1},"end":{"line":18,"column":1}},"key":"REXot8GCIj"}],"key":"t4mdLR2J3N"}],"key":"tHiAGVuUdD"}],"key":"RxEmCWGQLl"},{"type":"heading","depth":2,"position":{"start":{"line":20,"column":1},"end":{"line":20,"column":1}},"children":[{"type":"text","value":"Materials","position":{"start":{"line":20,"column":1},"end":{"line":20,"column":1}},"key":"hx8nSEwWrq"}],"identifier":"materials","label":"Materials","html_id":"materials","implicit":true,"key":"h24IgaWSma"},{"type":"heading","depth":2,"position":{"start":{"line":23,"column":1},"end":{"line":23,"column":1}},"children":[{"type":"text","value":"Schedule","position":{"start":{"line":23,"column":1},"end":{"line":23,"column":1}},"key":"aG8rshveTe"}],"identifier":"schedule","label":"Schedule","html_id":"schedule","implicit":true,"key":"gMgqGQLL3L"},{"type":"paragraph","position":{"start":{"line":25,"column":1},"end":{"line":25,"column":1}},"children":[{"type":"text","value":"Please see below for our current optimistic schedule. Depending on our progress, potential problems and different forms of learning, content and times might change a bit. Each lecture will be divided into several parts separated by a 5-10 minute break and might constitute a transition from basic to advanced concepts, theoretic to practical sessions and individual to group work. The different parts are roughly indicated in the schedule below like this:","position":{"start":{"line":25,"column":1},"end":{"line":25,"column":1}},"key":"rYh6QIRQxS"}],"key":"pzJVNT3j5s"},{"type":"table","position":{"start":{"line":29,"column":1},"end":{"line":31,"column":1}},"children":[{"type":"tableRow","position":{"start":{"line":29,"column":1},"end":{"line":29,"column":1}},"children":[{"type":"tableCell","header":true,"position":{"start":{"line":29,"column":1},"end":{"line":29,"column":1}},"children":[{"type":"text","value":"Date (day/month/year) 🗓","position":{"start":{"line":29,"column":1},"end":{"line":29,"column":1}},"key":"OGQQxzGmUW"}],"key":"mYBrDiC9Xe"},{"type":"tableCell","header":true,"position":{"start":{"line":29,"column":1},"end":{"line":29,"column":1}},"children":[{"type":"text","value":"Topic","position":{"start":{"line":29,"column":1},"end":{"line":29,"column":1}},"key":"K9DEFZ42JA"}],"key":"GhIMwdvHy4"},{"type":"tableCell","header":true,"position":{"start":{"line":29,"column":1},"end":{"line":29,"column":1}},"children":[{"type":"text","value":"Assignment / deadline","position":{"start":{"line":29,"column":1},"end":{"line":29,"column":1}},"key":"nv14RvMK5S"}],"key":"NMfocBaeUx"}],"key":"A5Yi8VWDfE"},{"type":"tableRow","position":{"start":{"line":31,"column":1},"end":{"line":31,"column":1}},"children":[{"type":"tableCell","position":{"start":{"line":31,"column":1},"end":{"line":31,"column":1}},"children":[{"type":"text","value":"28/10/2022","position":{"start":{"line":31,"column":1},"end":{"line":31,"column":1}},"key":"kI2ZJpY1Kd"}],"key":"vvZsPPaAy4"},{"type":"tableCell","position":{"start":{"line":31,"column":1},"end":{"line":31,"column":1}},"children":[{"type":"text","value":"Introduction I - course information & setup","position":{"start":{"line":31,"column":1},"end":{"line":31,"column":1}},"key":"DStBNX1qn9"}],"key":"cyS2A00mHo"},{"type":"tableCell","position":{"start":{"line":31,"column":1},"end":{"line":31,"column":1}},"children":[{"type":"text","value":"/not applicable","position":{"start":{"line":31,"column":1},"end":{"line":31,"column":1}},"key":"pUqg1a2Ffg"}],"key":"RkCUwl5Ili"}],"key":"JWw9zgvU6l"}],"key":"vKOa1N1MjR"}],"key":"xjRlYRscho"}],"key":"wuf9AigUg3"},"references":{"cite":{"order":[],"data":{}}},"footer":{"navigation":{"prev":{"title":"Setup for the course","url":"/setup","group":"Course Template for ressources in higher education"},"next":{"title":"Introduction to content X","url":"/intro-content","group":"Course Template for ressources in higher education"}}},"domain":"http://localhost:3000"}